{
	"backtraceGraph" : 
	{
		"commands" : 
		[
			"install",
			"serenity_install_headers",
			"serenity_lib",
			"serenity_install_sources"
		],
		"files" : 
		[
			"Meta/CMake/utils.cmake",
			"Userland/Libraries/LibSyntax/CMakeLists.txt"
		],
		"nodes" : 
		[
			{
				"file" : 1
			},
			{
				"command" : 2,
				"file" : 1,
				"line" : 5,
				"parent" : 0
			},
			{
				"command" : 1,
				"file" : 0,
				"line" : 37,
				"parent" : 1
			},
			{
				"command" : 0,
				"file" : 0,
				"line" : 9,
				"parent" : 2
			},
			{
				"command" : 0,
				"file" : 0,
				"line" : 9,
				"parent" : 2
			},
			{
				"command" : 0,
				"file" : 0,
				"line" : 9,
				"parent" : 2
			},
			{
				"command" : 3,
				"file" : 0,
				"line" : 38,
				"parent" : 1
			},
			{
				"command" : 0,
				"file" : 0,
				"line" : 21,
				"parent" : 6
			},
			{
				"command" : 0,
				"file" : 0,
				"line" : 21,
				"parent" : 6
			},
			{
				"command" : 0,
				"file" : 0,
				"line" : 21,
				"parent" : 6
			},
			{
				"command" : 0,
				"file" : 0,
				"line" : 21,
				"parent" : 6
			},
			{
				"command" : 0,
				"file" : 0,
				"line" : 42,
				"parent" : 1
			}
		]
	},
	"installers" : 
	[
		{
			"backtrace" : 3,
			"component" : "Unspecified",
			"destination" : "usr/include/LibSyntax",
			"isOptional" : true,
			"paths" : 
			[
				"Userland/Libraries/LibSyntax/Forward.h"
			],
			"type" : "file"
		},
		{
			"backtrace" : 4,
			"component" : "Unspecified",
			"destination" : "usr/include/LibSyntax",
			"isOptional" : true,
			"paths" : 
			[
				"Userland/Libraries/LibSyntax/Highlighter.h"
			],
			"type" : "file"
		},
		{
			"backtrace" : 5,
			"component" : "Unspecified",
			"destination" : "usr/include/LibSyntax",
			"isOptional" : true,
			"paths" : 
			[
				"Userland/Libraries/LibSyntax/HighlighterClient.h"
			],
			"type" : "file"
		},
		{
			"backtrace" : 7,
			"component" : "Unspecified",
			"destination" : "usr/src/serenity/Userland/Libraries/LibSyntax",
			"isOptional" : true,
			"paths" : 
			[
				"Userland/Libraries/LibSyntax/Forward.h"
			],
			"type" : "file"
		},
		{
			"backtrace" : 8,
			"component" : "Unspecified",
			"destination" : "usr/src/serenity/Userland/Libraries/LibSyntax",
			"isOptional" : true,
			"paths" : 
			[
				"Userland/Libraries/LibSyntax/Highlighter.cpp"
			],
			"type" : "file"
		},
		{
			"backtrace" : 9,
			"component" : "Unspecified",
			"destination" : "usr/src/serenity/Userland/Libraries/LibSyntax",
			"isOptional" : true,
			"paths" : 
			[
				"Userland/Libraries/LibSyntax/Highlighter.h"
			],
			"type" : "file"
		},
		{
			"backtrace" : 10,
			"component" : "Unspecified",
			"destination" : "usr/src/serenity/Userland/Libraries/LibSyntax",
			"isOptional" : true,
			"paths" : 
			[
				"Userland/Libraries/LibSyntax/HighlighterClient.h"
			],
			"type" : "file"
		},
		{
			"backtrace" : 11,
			"component" : "Unspecified",
			"destination" : "usr/lib",
			"isOptional" : true,
			"paths" : 
			[
				"Userland/Libraries/LibSyntax/libsyntax.so.serenity"
			],
			"targetId" : "LibSyntax::@b409d454b8b01e41a3d1",
			"targetIndex" : 394,
			"targetInstallNamelink" : "skip",
			"type" : "target"
		},
		{
			"backtrace" : 11,
			"component" : "Unspecified",
			"destination" : "usr/lib",
			"isOptional" : true,
			"paths" : 
			[
				"Userland/Libraries/LibSyntax/libsyntax.so"
			],
			"targetId" : "LibSyntax::@b409d454b8b01e41a3d1",
			"targetIndex" : 394,
			"targetInstallNamelink" : "only",
			"type" : "target"
		}
	],
	"paths" : 
	{
		"build" : "Userland/Libraries/LibSyntax",
		"source" : "Userland/Libraries/LibSyntax"
	}
}
